stringops/__init__.py
stringops/exceptions.py
stringops/manipulation.py
stringops/read.py
stringops-1.1.dist-info/LICENSE
stringops-1.1.dist-info/METADATA
stringops-1.1.dist-info/WHEEL
stringops-1.1.dist-info/top_level.txt
stringops-1.1.dist-info/RECORD
